LICENSE
MANIFEST.in
README.rst
setup.py
django_intl_tel_input2.egg-info/PKG-INFO
django_intl_tel_input2.egg-info/SOURCES.txt
django_intl_tel_input2.egg-info/dependency_links.txt
django_intl_tel_input2.egg-info/requires.txt
django_intl_tel_input2.egg-info/top_level.txt
intl_tel_input/__init__.py
intl_tel_input/widgets.py
intl_tel_input/static/intl_tel_input/init.js